rscylla/__init__.py
rscylla/cql.py
rscylla-0.0.1.dist-info/METADATA
rscylla-0.0.1.dist-info/WHEEL
rscylla-0.0.1.dist-info/top_level.txt
rscylla-0.0.1.dist-info/RECORD
